{
	"textures": {
		"0": "animated_java:item/iron_maiden/iron_maiden"
	},
	"elements": [
		{
			"from": [
				5.500559910414333,
				-3.4759238521836515,
				7.905935050391939
			],
			"to": [
				10.553191489361701,
				11.681970884658455,
				10.432250839865622
			],
			"rotation": {
				"angle": 0,
				"axis": "y",
				"origin": [
					8.026875699888018,
					-3.4759238521836515,
					-0.30459126539753534
				]
			},
			"faces": {
				"north": {
					"uv": [
						4.25,
						0,
						5.25,
						3
					],
					"texture": "#0"
				},
				"east": {
					"uv": [
						4.25,
						6,
						4.75,
						9
					],
					"texture": "#0"
				},
				"south": {
					"uv": [
						4.25,
						3,
						5.25,
						6
					],
					"texture": "#0"
				},
				"west": {
					"uv": [
						4.75,
						6,
						5.25,
						9
					],
					"texture": "#0"
				},
				"up": {
					"uv": [
						8.75,
						11.75,
						7.75,
						11.25
					],
					"texture": "#0"
				},
				"down": {
					"uv": [
						11.875,
						11.25,
						10.875,
						11.75
					],
					"texture": "#0"
				}
			}
		},
		{
			"from": [
				11.97424412094065,
				8.681970884658455,
				7.274356103023518
			],
			"to": [
				12.290033594624859,
				8.997760358342664,
				7.905935050391939
			],
			"rotation": {
				"angle": 0,
				"axis": "y",
				"origin": [
					8.026875699888018,
					-3.4759238521836515,
					-0.30459126539753534
				]
			},
			"faces": {
				"north": {
					"uv": [
						2.25,
						13.625,
						2.3125,
						13.6875
					],
					"texture": "#0"
				},
				"east": {
					"uv": [
						13.375,
						11.625,
						13.5,
						11.6875
					],
					"texture": "#0"
				},
				"south": {
					"uv": [
						2.375,
						13.625,
						2.4375,
						13.6875
					],
					"texture": "#0"
				},
				"west": {
					"uv": [
						11.75,
						13.375,
						11.875,
						13.4375
					],
					"texture": "#0"
				},
				"up": {
					"uv": [
						13.4375,
						11.875,
						13.375,
						11.75
					],
					"texture": "#0"
				},
				"down": {
					"uv": [
						11.9375,
						13.375,
						11.875,
						13.5
					],
					"texture": "#0"
				}
			}
		},
		{
			"from": [
				10.079507278835386,
				8.681970884658455,
				7.274356103023518
			],
			"to": [
				10.395296752519597,
				8.997760358342664,
				7.905935050391939
			],
			"rotation": {
				"angle": 0,
				"axis": "y",
				"origin": [
					8.026875699888018,
					-3.4759238521836515,
					-0.30459126539753534
				]
			},
			"faces": {
				"north": {
					"uv": [
						2.5,
						13.625,
						2.5625,
						13.6875
					],
					"texture": "#0"
				},
				"east": {
					"uv": [
						13.375,
						11.875,
						13.5,
						11.9375
					],
					"texture": "#0"
				},
				"south": {
					"uv": [
						2.625,
						13.625,
						2.6875,
						13.6875
					],
					"texture": "#0"
				},
				"west": {
					"uv": [
						12,
						13.375,
						12.125,
						13.4375
					],
					"texture": "#0"
				},
				"up": {
					"uv": [
						13.4375,
						12.125,
						13.375,
						12
					],
					"texture": "#0"
				},
				"down": {
					"uv": [
						12.1875,
						13.375,
						12.125,
						13.5
					],
					"texture": "#0"
				}
			}
		},
		{
			"from": [
				11.97424412094065,
				4.892497200447927,
				7.274356103023518
			],
			"to": [
				12.290033594624859,
				5.208286674132138,
				7.905935050391939
			],
			"rotation": {
				"angle": 0,
				"axis": "y",
				"origin": [
					8.026875699888018,
					-3.4759238521836515,
					-0.30459126539753534
				]
			},
			"faces": {
				"north": {
					"uv": [
						6.875,
						13.625,
						6.9375,
						13.6875
					],
					"texture": "#0"
				},
				"east": {
					"uv": [
						13.5,
						9.125,
						13.625,
						9.1875
					],
					"texture": "#0"
				},
				"south": {
					"uv": [
						7,
						13.625,
						7.0625,
						13.6875
					],
					"texture": "#0"
				},
				"west": {
					"uv": [
						9.25,
						13.5,
						9.375,
						13.5625
					],
					"texture": "#0"
				},
				"up": {
					"uv": [
						9.4375,
						13.625,
						9.375,
						13.5
					],
					"texture": "#0"
				},
				"down": {
					"uv": [
						9.5625,
						13.5,
						9.5,
						13.625
					],
					"texture": "#0"
				}
			}
		},
		{
			"from": [
				10.079507278835386,
				4.892497200447927,
				7.274356103023518
			],
			"to": [
				10.395296752519597,
				5.208286674132138,
				7.905935050391939
			],
			"rotation": {
				"angle": 0,
				"axis": "y",
				"origin": [
					8.026875699888018,
					-3.4759238521836515,
					-0.30459126539753534
				]
			},
			"faces": {
				"north": {
					"uv": [
						6.625,
						13.625,
						6.6875,
						13.6875
					],
					"texture": "#0"
				},
				"east": {
					"uv": [
						13.5,
						8.625,
						13.625,
						8.6875
					],
					"texture": "#0"
				},
				"south": {
					"uv": [
						6.75,
						13.625,
						6.8125,
						13.6875
					],
					"texture": "#0"
				},
				"west": {
					"uv": [
						13.5,
						8.75,
						13.625,
						8.8125
					],
					"texture": "#0"
				},
				"up": {
					"uv": [
						13.5625,
						9,
						13.5,
						8.875
					],
					"texture": "#0"
				},
				"down": {
					"uv": [
						13.5625,
						9,
						13.5,
						9.125
					],
					"texture": "#0"
				}
			}
		},
		{
			"from": [
				3.7637178051511766,
				6.787234042553191,
				7.274356103023518
			],
			"to": [
				4.079507278835386,
				7.103023516237402,
				7.905935050391939
			],
			"rotation": {
				"angle": 0,
				"axis": "y",
				"origin": [
					8.026875699888018,
					-3.4759238521836515,
					-0.30459126539753534
				]
			},
			"faces": {
				"north": {
					"uv": [
						5.75,
						13.625,
						5.8125,
						13.6875
					],
					"texture": "#0"
				},
				"east": {
					"uv": [
						6.125,
						13.5,
						6.25,
						13.5625
					],
					"texture": "#0"
				},
				"south": {
					"uv": [
						13.625,
						5.75,
						13.6875,
						5.8125
					],
					"texture": "#0"
				},
				"west": {
					"uv": [
						13.5,
						6.125,
						13.625,
						6.1875
					],
					"texture": "#0"
				},
				"up": {
					"uv": [
						13.5625,
						6.375,
						13.5,
						6.25
					],
					"texture": "#0"
				},
				"down": {
					"uv": [
						13.5625,
						6.375,
						13.5,
						6.5
					],
					"texture": "#0"
				}
			}
		},
		{
			"from": [
				5.658454647256439,
				6.787234042553191,
				7.274356103023518
			],
			"to": [
				5.97424412094065,
				7.103023516237402,
				7.905935050391939
			],
			"rotation": {
				"angle": 0,
				"axis": "y",
				"origin": [
					8.026875699888018,
					-3.4759238521836515,
					-0.30459126539753534
				]
			},
			"faces": {
				"north": {
					"uv": [
						5.5,
						13.625,
						5.5625,
						13.6875
					],
					"texture": "#0"
				},
				"east": {
					"uv": [
						5.75,
						13.5,
						5.875,
						13.5625
					],
					"texture": "#0"
				},
				"south": {
					"uv": [
						5.625,
						13.625,
						5.6875,
						13.6875
					],
					"texture": "#0"
				},
				"west": {
					"uv": [
						5.875,
						13.5,
						6,
						13.5625
					],
					"texture": "#0"
				},
				"up": {
					"uv": [
						6.0625,
						13.625,
						6,
						13.5
					],
					"texture": "#0"
				},
				"down": {
					"uv": [
						13.5625,
						6,
						13.5,
						6.125
					],
					"texture": "#0"
				}
			}
		},
		{
			"from": [
				9.447928331466965,
				10.576707726763717,
				7.274356103023518
			],
			"to": [
				9.763717805151176,
				10.892497200447927,
				7.905935050391939
			],
			"rotation": {
				"angle": 0,
				"axis": "y",
				"origin": [
					8.026875699888018,
					-3.4759238521836515,
					-0.30459126539753534
				]
			},
			"faces": {
				"north": {
					"uv": [
						5.375,
						13.625,
						5.4375,
						13.6875
					],
					"texture": "#0"
				},
				"east": {
					"uv": [
						13.5,
						5.25,
						13.625,
						5.3125
					],
					"texture": "#0"
				},
				"south": {
					"uv": [
						13.625,
						5.375,
						13.6875,
						5.4375
					],
					"texture": "#0"
				},
				"west": {
					"uv": [
						5.375,
						13.5,
						5.5,
						13.5625
					],
					"texture": "#0"
				},
				"up": {
					"uv": [
						5.5625,
						13.625,
						5.5,
						13.5
					],
					"texture": "#0"
				},
				"down": {
					"uv": [
						5.6875,
						13.5,
						5.625,
						13.625
					],
					"texture": "#0"
				}
			}
		},
		{
			"from": [
				11.342665173572229,
				10.576707726763717,
				7.274356103023518
			],
			"to": [
				11.65845464725644,
				10.892497200447927,
				7.905935050391939
			],
			"rotation": {
				"angle": 0,
				"axis": "y",
				"origin": [
					8.026875699888018,
					-3.4759238521836515,
					-0.30459126539753534
				]
			},
			"faces": {
				"north": {
					"uv": [
						6,
						13.625,
						6.0625,
						13.6875
					],
					"texture": "#0"
				},
				"east": {
					"uv": [
						13.5,
						7.375,
						13.625,
						7.4375
					],
					"texture": "#0"
				},
				"south": {
					"uv": [
						13.625,
						6,
						13.6875,
						6.0625
					],
					"texture": "#0"
				},
				"west": {
					"uv": [
						13.5,
						7.5,
						13.625,
						7.5625
					],
					"texture": "#0"
				},
				"up": {
					"uv": [
						13.5625,
						7.75,
						13.5,
						7.625
					],
					"texture": "#0"
				},
				"down": {
					"uv": [
						13.5625,
						7.75,
						13.5,
						7.875
					],
					"texture": "#0"
				}
			}
		},
		{
			"from": [
				5.658454647256439,
				10.576707726763717,
				7.274356103023518
			],
			"to": [
				5.97424412094065,
				10.892497200447927,
				7.905935050391939
			],
			"rotation": {
				"angle": 0,
				"axis": "y",
				"origin": [
					8.026875699888018,
					-3.4759238521836515,
					-0.30459126539753534
				]
			},
			"faces": {
				"north": {
					"uv": [
						13.625,
						6.25,
						13.6875,
						6.3125
					],
					"texture": "#0"
				},
				"east": {
					"uv": [
						8.125,
						13.5,
						8.25,
						13.5625
					],
					"texture": "#0"
				},
				"south": {
					"uv": [
						6.375,
						13.625,
						6.4375,
						13.6875
					],
					"texture": "#0"
				},
				"west": {
					"uv": [
						13.5,
						8.125,
						13.625,
						8.1875
					],
					"texture": "#0"
				},
				"up": {
					"uv": [
						8.3125,
						13.625,
						8.25,
						13.5
					],
					"texture": "#0"
				},
				"down": {
					"uv": [
						13.5625,
						8.25,
						13.5,
						8.375
					],
					"texture": "#0"
				}
			}
		},
		{
			"from": [
				3.7637178051511766,
				10.576707726763717,
				7.274356103023518
			],
			"to": [
				4.079507278835386,
				10.892497200447927,
				7.905935050391939
			],
			"rotation": {
				"angle": 0,
				"axis": "y",
				"origin": [
					8.026875699888018,
					-3.4759238521836515,
					-0.30459126539753534
				]
			},
			"faces": {
				"north": {
					"uv": [
						6.125,
						13.625,
						6.1875,
						13.6875
					],
					"texture": "#0"
				},
				"east": {
					"uv": [
						7.875,
						13.5,
						8,
						13.5625
					],
					"texture": "#0"
				},
				"south": {
					"uv": [
						13.625,
						6.125,
						13.6875,
						6.1875
					],
					"texture": "#0"
				},
				"west": {
					"uv": [
						13.5,
						7.875,
						13.625,
						7.9375
					],
					"texture": "#0"
				},
				"up": {
					"uv": [
						8.0625,
						13.625,
						8,
						13.5
					],
					"texture": "#0"
				},
				"down": {
					"uv": [
						13.5625,
						8,
						13.5,
						8.125
					],
					"texture": "#0"
				}
			}
		},
		{
			"from": [
				7.553191489361702,
				10.576707726763717,
				7.274356103023518
			],
			"to": [
				7.868980963045913,
				10.892497200447927,
				7.905935050391939
			],
			"rotation": {
				"angle": 0,
				"axis": "y",
				"origin": [
					8.026875699888018,
					-3.4759238521836515,
					-0.30459126539753534
				]
			},
			"faces": {
				"north": {
					"uv": [
						5.25,
						13.625,
						5.3125,
						13.6875
					],
					"texture": "#0"
				},
				"east": {
					"uv": [
						4.875,
						13.5,
						5,
						13.5625
					],
					"texture": "#0"
				},
				"south": {
					"uv": [
						13.625,
						5.25,
						13.6875,
						5.3125
					],
					"texture": "#0"
				},
				"west": {
					"uv": [
						13.5,
						5,
						13.625,
						5.0625
					],
					"texture": "#0"
				},
				"up": {
					"uv": [
						13.5625,
						5.25,
						13.5,
						5.125
					],
					"texture": "#0"
				},
				"down": {
					"uv": [
						5.3125,
						13.5,
						5.25,
						13.625
					],
					"texture": "#0"
				}
			}
		},
		{
			"from": [
				8.816349384098544,
				12.47144456886898,
				7.274356103023518
			],
			"to": [
				9.132138857782754,
				12.787234042553191,
				9.169092945128781
			],
			"rotation": {
				"angle": 0,
				"axis": "y",
				"origin": [
					8.026875699888018,
					-3.4759238521836515,
					-0.30459126539753534
				]
			},
			"faces": {
				"north": {
					"uv": [
						13.625,
						7.25,
						13.6875,
						7.3125
					],
					"texture": "#0"
				},
				"east": {
					"uv": [
						13.25,
						3.5,
						13.625,
						3.5625
					],
					"texture": "#0"
				},
				"south": {
					"uv": [
						13.625,
						7.375,
						13.6875,
						7.4375
					],
					"texture": "#0"
				},
				"west": {
					"uv": [
						13.25,
						3.625,
						13.625,
						3.6875
					],
					"texture": "#0"
				},
				"up": {
					"uv": [
						0.9375,
						13.625,
						0.875,
						13.25
					],
					"texture": "#0"
				},
				"down": {
					"uv": [
						1.9375,
						13.25,
						1.875,
						13.625
					],
					"texture": "#0"
				}
			}
		},
		{
			"from": [
				6.921612541993281,
				12.47144456886898,
				7.274356103023518
			],
			"to": [
				7.237402015677492,
				12.787234042553191,
				9.169092945128781
			],
			"rotation": {
				"angle": 0,
				"axis": "y",
				"origin": [
					8.026875699888018,
					-3.4759238521836515,
					-0.30459126539753534
				]
			},
			"faces": {
				"north": {
					"uv": [
						13.625,
						7.5,
						13.6875,
						7.5625
					],
					"texture": "#0"
				},
				"east": {
					"uv": [
						13.25,
						3.75,
						13.625,
						3.8125
					],
					"texture": "#0"
				},
				"south": {
					"uv": [
						7.625,
						13.625,
						7.6875,
						13.6875
					],
					"texture": "#0"
				},
				"west": {
					"uv": [
						13.25,
						3.875,
						13.625,
						3.9375
					],
					"texture": "#0"
				},
				"up": {
					"uv": [
						13.3125,
						5.375,
						13.25,
						5
					],
					"texture": "#0"
				},
				"down": {
					"uv": [
						6.4375,
						13.25,
						6.375,
						13.625
					],
					"texture": "#0"
				}
			}
		},
		{
			"from": [
				6.29003359462486,
				13.734602463605821,
				7.274356103023518
			],
			"to": [
				6.60582306830907,
				14.050391937290033,
				9.169092945128781
			],
			"rotation": {
				"angle": 0,
				"axis": "y",
				"origin": [
					8.026875699888018,
					-3.4759238521836515,
					-0.30459126539753534
				]
			},
			"faces": {
				"north": {
					"uv": [
						13.625,
						7.75,
						13.6875,
						7.8125
					],
					"texture": "#0"
				},
				"east": {
					"uv": [
						13.25,
						5.375,
						13.625,
						5.4375
					],
					"texture": "#0"
				},
				"south": {
					"uv": [
						7.875,
						13.625,
						7.9375,
						13.6875
					],
					"texture": "#0"
				},
				"west": {
					"uv": [
						13.25,
						5.75,
						13.625,
						5.8125
					],
					"texture": "#0"
				},
				"up": {
					"uv": [
						6.8125,
						13.625,
						6.75,
						13.25
					],
					"texture": "#0"
				},
				"down": {
					"uv": [
						6.9375,
						13.25,
						6.875,
						13.625
					],
					"texture": "#0"
				}
			}
		},
		{
			"from": [
				8.184770436730123,
				13.734602463605821,
				7.274356103023518
			],
			"to": [
				8.500559910414333,
				14.050391937290033,
				9.169092945128781
			],
			"rotation": {
				"angle": 0,
				"axis": "y",
				"origin": [
					8.026875699888018,
					-3.4759238521836515,
					-0.30459126539753534
				]
			},
			"faces": {
				"north": {
					"uv": [
						13.625,
						7.625,
						13.6875,
						7.6875
					],
					"texture": "#0"
				},
				"east": {
					"uv": [
						13.25,
						4,
						13.625,
						4.0625
					],
					"texture": "#0"
				},
				"south": {
					"uv": [
						7.75,
						13.625,
						7.8125,
						13.6875
					],
					"texture": "#0"
				},
				"west": {
					"uv": [
						13.25,
						4.125,
						13.625,
						4.1875
					],
					"texture": "#0"
				},
				"up": {
					"uv": [
						6.5625,
						13.625,
						6.5,
						13.25
					],
					"texture": "#0"
				},
				"down": {
					"uv": [
						6.6875,
						13.25,
						6.625,
						13.625
					],
					"texture": "#0"
				}
			}
		},
		{
			"from": [
				6.921612541993281,
				14.997760358342664,
				7.274356103023518
			],
			"to": [
				7.237402015677492,
				15.313549832026874,
				9.169092945128781
			],
			"rotation": {
				"angle": 0,
				"axis": "y",
				"origin": [
					8.026875699888018,
					-3.4759238521836515,
					-0.30459126539753534
				]
			},
			"faces": {
				"north": {
					"uv": [
						13.625,
						8,
						13.6875,
						8.0625
					],
					"texture": "#0"
				},
				"east": {
					"uv": [
						7.875,
						13.25,
						8.25,
						13.3125
					],
					"texture": "#0"
				},
				"south": {
					"uv": [
						8.125,
						13.625,
						8.1875,
						13.6875
					],
					"texture": "#0"
				},
				"west": {
					"uv": [
						8.25,
						13.25,
						8.625,
						13.3125
					],
					"texture": "#0"
				},
				"up": {
					"uv": [
						13.3125,
						8.625,
						13.25,
						8.25
					],
					"texture": "#0"
				},
				"down": {
					"uv": [
						9.1875,
						13.25,
						9.125,
						13.625
					],
					"texture": "#0"
				}
			}
		},
		{
			"from": [
				8.816349384098544,
				14.997760358342664,
				7.274356103023518
			],
			"to": [
				9.132138857782754,
				15.313549832026874,
				9.169092945128781
			],
			"rotation": {
				"angle": 0,
				"axis": "y",
				"origin": [
					8.026875699888018,
					-3.4759238521836515,
					-0.30459126539753534
				]
			},
			"faces": {
				"north": {
					"uv": [
						13.625,
						7.875,
						13.6875,
						7.9375
					],
					"texture": "#0"
				},
				"east": {
					"uv": [
						13.25,
						5.875,
						13.625,
						5.9375
					],
					"texture": "#0"
				},
				"south": {
					"uv": [
						8,
						13.625,
						8.0625,
						13.6875
					],
					"texture": "#0"
				},
				"west": {
					"uv": [
						7,
						13.25,
						7.375,
						13.3125
					],
					"texture": "#0"
				},
				"up": {
					"uv": [
						7.6875,
						13.625,
						7.625,
						13.25
					],
					"texture": "#0"
				},
				"down": {
					"uv": [
						7.8125,
						13.25,
						7.75,
						13.625
					],
					"texture": "#0"
				}
			}
		},
		{
			"from": [
				8.184770436730123,
				8.681970884658455,
				7.274356103023518
			],
			"to": [
				8.500559910414333,
				8.997760358342664,
				7.905935050391939
			],
			"rotation": {
				"angle": 0,
				"axis": "y",
				"origin": [
					8.026875699888018,
					-3.4759238521836515,
					-0.30459126539753534
				]
			},
			"faces": {
				"north": {
					"uv": [
						2.75,
						13.625,
						2.8125,
						13.6875
					],
					"texture": "#0"
				},
				"east": {
					"uv": [
						13.375,
						12.125,
						13.5,
						12.1875
					],
					"texture": "#0"
				},
				"south": {
					"uv": [
						2.875,
						13.625,
						2.9375,
						13.6875
					],
					"texture": "#0"
				},
				"west": {
					"uv": [
						12.25,
						13.375,
						12.375,
						13.4375
					],
					"texture": "#0"
				},
				"up": {
					"uv": [
						13.4375,
						12.375,
						13.375,
						12.25
					],
					"texture": "#0"
				},
				"down": {
					"uv": [
						13.4375,
						12.375,
						13.375,
						12.5
					],
					"texture": "#0"
				}
			}
		},
		{
			"from": [
				6.29003359462486,
				8.681970884658455,
				7.274356103023518
			],
			"to": [
				6.60582306830907,
				8.997760358342664,
				7.905935050391939
			],
			"rotation": {
				"angle": 0,
				"axis": "y",
				"origin": [
					8.026875699888018,
					-3.4759238521836515,
					-0.30459126539753534
				]
			},
			"faces": {
				"north": {
					"uv": [
						3.25,
						13.625,
						3.3125,
						13.6875
					],
					"texture": "#0"
				},
				"east": {
					"uv": [
						13.375,
						12.5,
						13.5,
						12.5625
					],
					"texture": "#0"
				},
				"south": {
					"uv": [
						3.375,
						13.625,
						3.4375,
						13.6875
					],
					"texture": "#0"
				},
				"west": {
					"uv": [
						12.625,
						13.375,
						12.75,
						13.4375
					],
					"texture": "#0"
				},
				"up": {
					"uv": [
						13.4375,
						12.75,
						13.375,
						12.625
					],
					"texture": "#0"
				},
				"down": {
					"uv": [
						12.8125,
						13.375,
						12.75,
						13.5
					],
					"texture": "#0"
				}
			}
		},
		{
			"from": [
				4.395296752519597,
				8.681970884658455,
				7.274356103023518
			],
			"to": [
				4.711086226203808,
				8.997760358342664,
				7.905935050391939
			],
			"rotation": {
				"angle": 0,
				"axis": "y",
				"origin": [
					8.026875699888018,
					-3.4759238521836515,
					-0.30459126539753534
				]
			},
			"faces": {
				"north": {
					"uv": [
						5.875,
						13.625,
						5.9375,
						13.6875
					],
					"texture": "#0"
				},
				"east": {
					"uv": [
						7,
						13.5,
						7.125,
						13.5625
					],
					"texture": "#0"
				},
				"south": {
					"uv": [
						13.625,
						5.875,
						13.6875,
						5.9375
					],
					"texture": "#0"
				},
				"west": {
					"uv": [
						7.125,
						13.5,
						7.25,
						13.5625
					],
					"texture": "#0"
				},
				"up": {
					"uv": [
						7.3125,
						13.625,
						7.25,
						13.5
					],
					"texture": "#0"
				},
				"down": {
					"uv": [
						13.5625,
						7.25,
						13.5,
						7.375
					],
					"texture": "#0"
				}
			}
		},
		{
			"from": [
				9.447928331466965,
				6.787234042553191,
				7.274356103023518
			],
			"to": [
				9.763717805151176,
				7.103023516237402,
				7.905935050391939
			],
			"rotation": {
				"angle": 0,
				"axis": "y",
				"origin": [
					8.026875699888018,
					-3.4759238521836515,
					-0.30459126539753534
				]
			},
			"faces": {
				"north": {
					"uv": [
						3.625,
						13.625,
						3.6875,
						13.6875
					],
					"texture": "#0"
				},
				"east": {
					"uv": [
						13.375,
						13,
						13.5,
						13.0625
					],
					"texture": "#0"
				},
				"south": {
					"uv": [
						13.625,
						3.625,
						13.6875,
						3.6875
					],
					"texture": "#0"
				},
				"west": {
					"uv": [
						13.125,
						13.375,
						13.25,
						13.4375
					],
					"texture": "#0"
				},
				"up": {
					"uv": [
						13.4375,
						13.25,
						13.375,
						13.125
					],
					"texture": "#0"
				},
				"down": {
					"uv": [
						13.3125,
						13.375,
						13.25,
						13.5
					],
					"texture": "#0"
				}
			}
		},
		{
			"from": [
				11.342665173572229,
				6.787234042553191,
				7.274356103023518
			],
			"to": [
				11.65845464725644,
				7.103023516237402,
				7.905935050391939
			],
			"rotation": {
				"angle": 0,
				"axis": "y",
				"origin": [
					8.026875699888018,
					-3.4759238521836515,
					-0.30459126539753534
				]
			},
			"faces": {
				"north": {
					"uv": [
						13.625,
						6.375,
						13.6875,
						6.4375
					],
					"texture": "#0"
				},
				"east": {
					"uv": [
						8.375,
						13.5,
						8.5,
						13.5625
					],
					"texture": "#0"
				},
				"south": {
					"uv": [
						6.5,
						13.625,
						6.5625,
						13.6875
					],
					"texture": "#0"
				},
				"west": {
					"uv": [
						13.5,
						8.375,
						13.625,
						8.4375
					],
					"texture": "#0"
				},
				"up": {
					"uv": [
						8.5625,
						13.625,
						8.5,
						13.5
					],
					"texture": "#0"
				},
				"down": {
					"uv": [
						13.5625,
						8.5,
						13.5,
						8.625
					],
					"texture": "#0"
				}
			}
		},
		{
			"from": [
				7.553191489361702,
				6.787234042553191,
				7.274356103023518
			],
			"to": [
				7.868980963045913,
				7.103023516237402,
				7.905935050391939
			],
			"rotation": {
				"angle": 0,
				"axis": "y",
				"origin": [
					8.026875699888018,
					-3.4759238521836515,
					-0.30459126539753534
				]
			},
			"faces": {
				"north": {
					"uv": [
						3.5,
						13.625,
						3.5625,
						13.6875
					],
					"texture": "#0"
				},
				"east": {
					"uv": [
						13.375,
						12.75,
						13.5,
						12.8125
					],
					"texture": "#0"
				},
				"south": {
					"uv": [
						13.625,
						3.5,
						13.6875,
						3.5625
					],
					"texture": "#0"
				},
				"west": {
					"uv": [
						12.875,
						13.375,
						13,
						13.4375
					],
					"texture": "#0"
				},
				"up": {
					"uv": [
						13.4375,
						13,
						13.375,
						12.875
					],
					"texture": "#0"
				},
				"down": {
					"uv": [
						13.0625,
						13.375,
						13,
						13.5
					],
					"texture": "#0"
				}
			}
		},
		{
			"from": [
				8.184770436730123,
				4.892497200447927,
				7.274356103023518
			],
			"to": [
				8.500559910414333,
				5.208286674132138,
				7.905935050391939
			],
			"rotation": {
				"angle": 0,
				"axis": "y",
				"origin": [
					8.026875699888018,
					-3.4759238521836515,
					-0.30459126539753534
				]
			},
			"faces": {
				"north": {
					"uv": [
						3.875,
						13.625,
						3.9375,
						13.6875
					],
					"texture": "#0"
				},
				"east": {
					"uv": [
						0.25,
						13.5,
						0.375,
						13.5625
					],
					"texture": "#0"
				},
				"south": {
					"uv": [
						13.625,
						3.875,
						13.6875,
						3.9375
					],
					"texture": "#0"
				},
				"west": {
					"uv": [
						0.375,
						13.5,
						0.5,
						13.5625
					],
					"texture": "#0"
				},
				"up": {
					"uv": [
						0.5625,
						13.625,
						0.5,
						13.5
					],
					"texture": "#0"
				},
				"down": {
					"uv": [
						0.6875,
						13.5,
						0.625,
						13.625
					],
					"texture": "#0"
				}
			}
		},
		{
			"from": [
				6.29003359462486,
				4.892497200447927,
				7.274356103023518
			],
			"to": [
				6.60582306830907,
				5.208286674132138,
				7.905935050391939
			],
			"rotation": {
				"angle": 0,
				"axis": "y",
				"origin": [
					8.026875699888018,
					-3.4759238521836515,
					-0.30459126539753534
				]
			},
			"faces": {
				"north": {
					"uv": [
						3.75,
						13.625,
						3.8125,
						13.6875
					],
					"texture": "#0"
				},
				"east": {
					"uv": [
						13.375,
						13.25,
						13.5,
						13.3125
					],
					"texture": "#0"
				},
				"south": {
					"uv": [
						13.625,
						3.75,
						13.6875,
						3.8125
					],
					"texture": "#0"
				},
				"west": {
					"uv": [
						13.375,
						13.375,
						13.5,
						13.4375
					],
					"texture": "#0"
				},
				"up": {
					"uv": [
						0.0625,
						13.625,
						0,
						13.5
					],
					"texture": "#0"
				},
				"down": {
					"uv": [
						0.1875,
						13.5,
						0.125,
						13.625
					],
					"texture": "#0"
				}
			}
		},
		{
			"from": [
				4.395296752519597,
				4.892497200447927,
				7.274356103023518
			],
			"to": [
				4.711086226203808,
				5.208286674132138,
				7.905935050391939
			],
			"rotation": {
				"angle": 0,
				"axis": "y",
				"origin": [
					8.026875699888018,
					-3.4759238521836515,
					-0.30459126539753534
				]
			},
			"faces": {
				"north": {
					"uv": [
						7.125,
						13.625,
						7.1875,
						13.6875
					],
					"texture": "#0"
				},
				"east": {
					"uv": [
						13.5,
						9.5,
						13.625,
						9.5625
					],
					"texture": "#0"
				},
				"south": {
					"uv": [
						7.25,
						13.625,
						7.3125,
						13.6875
					],
					"texture": "#0"
				},
				"west": {
					"uv": [
						9.625,
						13.5,
						9.75,
						13.5625
					],
					"texture": "#0"
				},
				"up": {
					"uv": [
						13.5625,
						9.75,
						13.5,
						9.625
					],
					"texture": "#0"
				},
				"down": {
					"uv": [
						9.8125,
						13.5,
						9.75,
						13.625
					],
					"texture": "#0"
				}
			}
		},
		{
			"from": [
				8.184770436730123,
				-2.686450167973124,
				7.274356103023518
			],
			"to": [
				8.500559910414333,
				-2.3706606942889135,
				7.905935050391939
			],
			"rotation": {
				"angle": 0,
				"axis": "y",
				"origin": [
					8.026875699888018,
					-3.4759238521836515,
					-0.30459126539753534
				]
			},
			"faces": {
				"north": {
					"uv": [
						13.625,
						5,
						13.6875,
						5.0625
					],
					"texture": "#0"
				},
				"east": {
					"uv": [
						13.5,
						4.5,
						13.625,
						4.5625
					],
					"texture": "#0"
				},
				"south": {
					"uv": [
						13.625,
						5.125,
						13.6875,
						5.1875
					],
					"texture": "#0"
				},
				"west": {
					"uv": [
						4.625,
						13.5,
						4.75,
						13.5625
					],
					"texture": "#0"
				},
				"up": {
					"uv": [
						13.5625,
						4.75,
						13.5,
						4.625
					],
					"texture": "#0"
				},
				"down": {
					"uv": [
						4.8125,
						13.5,
						4.75,
						13.625
					],
					"texture": "#0"
				}
			}
		},
		{
			"from": [
				6.29003359462486,
				-2.686450167973124,
				7.274356103023518
			],
			"to": [
				6.60582306830907,
				-2.3706606942889135,
				7.905935050391939
			],
			"rotation": {
				"angle": 0,
				"axis": "y",
				"origin": [
					8.026875699888018,
					-3.4759238521836515,
					-0.30459126539753534
				]
			},
			"faces": {
				"north": {
					"uv": [
						4.75,
						13.625,
						4.8125,
						13.6875
					],
					"texture": "#0"
				},
				"east": {
					"uv": [
						13.5,
						4.25,
						13.625,
						4.3125
					],
					"texture": "#0"
				},
				"south": {
					"uv": [
						4.875,
						13.625,
						4.9375,
						13.6875
					],
					"texture": "#0"
				},
				"west": {
					"uv": [
						4.375,
						13.5,
						4.5,
						13.5625
					],
					"texture": "#0"
				},
				"up": {
					"uv": [
						13.5625,
						4.5,
						13.5,
						4.375
					],
					"texture": "#0"
				},
				"down": {
					"uv": [
						4.5625,
						13.5,
						4.5,
						13.625
					],
					"texture": "#0"
				}
			}
		},
		{
			"from": [
				9.447928331466965,
				-0.7917133258678621,
				7.274356103023518
			],
			"to": [
				9.763717805151176,
				-0.4759238521836515,
				7.905935050391939
			],
			"rotation": {
				"angle": 0,
				"axis": "y",
				"origin": [
					8.026875699888018,
					-3.4759238521836515,
					-0.30459126539753534
				]
			},
			"faces": {
				"north": {
					"uv": [
						4.625,
						13.625,
						4.6875,
						13.6875
					],
					"texture": "#0"
				},
				"east": {
					"uv": [
						3.875,
						13.5,
						4,
						13.5625
					],
					"texture": "#0"
				},
				"south": {
					"uv": [
						13.625,
						4.625,
						13.6875,
						4.6875
					],
					"texture": "#0"
				},
				"west": {
					"uv": [
						4,
						13.5,
						4.125,
						13.5625
					],
					"texture": "#0"
				},
				"up": {
					"uv": [
						4.1875,
						13.625,
						4.125,
						13.5
					],
					"texture": "#0"
				},
				"down": {
					"uv": [
						4.3125,
						13.5,
						4.25,
						13.625
					],
					"texture": "#0"
				}
			}
		},
		{
			"from": [
				7.553191489361702,
				-0.7917133258678621,
				7.274356103023518
			],
			"to": [
				7.868980963045913,
				-0.4759238521836515,
				7.905935050391939
			],
			"rotation": {
				"angle": 0,
				"axis": "y",
				"origin": [
					8.026875699888018,
					-3.4759238521836515,
					-0.30459126539753534
				]
			},
			"faces": {
				"north": {
					"uv": [
						4.5,
						13.625,
						4.5625,
						13.6875
					],
					"texture": "#0"
				},
				"east": {
					"uv": [
						3.375,
						13.5,
						3.5,
						13.5625
					],
					"texture": "#0"
				},
				"south": {
					"uv": [
						13.625,
						4.5,
						13.6875,
						4.5625
					],
					"texture": "#0"
				},
				"west": {
					"uv": [
						3.5,
						13.5,
						3.625,
						13.5625
					],
					"texture": "#0"
				},
				"up": {
					"uv": [
						3.6875,
						13.625,
						3.625,
						13.5
					],
					"texture": "#0"
				},
				"down": {
					"uv": [
						3.8125,
						13.5,
						3.75,
						13.625
					],
					"texture": "#0"
				}
			}
		},
		{
			"from": [
				9.447928331466965,
				2.9977603583426644,
				7.274356103023518
			],
			"to": [
				9.763717805151176,
				3.313549832026875,
				7.905935050391939
			],
			"rotation": {
				"angle": 0,
				"axis": "y",
				"origin": [
					8.026875699888018,
					-3.4759238521836515,
					-0.30459126539753534
				]
			},
			"faces": {
				"north": {
					"uv": [
						4.375,
						13.625,
						4.4375,
						13.6875
					],
					"texture": "#0"
				},
				"east": {
					"uv": [
						2.625,
						13.5,
						2.75,
						13.5625
					],
					"texture": "#0"
				},
				"south": {
					"uv": [
						13.625,
						4.375,
						13.6875,
						4.4375
					],
					"texture": "#0"
				},
				"west": {
					"uv": [
						2.75,
						13.5,
						2.875,
						13.5625
					],
					"texture": "#0"
				},
				"up": {
					"uv": [
						2.9375,
						13.625,
						2.875,
						13.5
					],
					"texture": "#0"
				},
				"down": {
					"uv": [
						3.3125,
						13.5,
						3.25,
						13.625
					],
					"texture": "#0"
				}
			}
		},
		{
			"from": [
				7.553191489361702,
				2.9977603583426644,
				7.274356103023518
			],
			"to": [
				7.868980963045913,
				3.313549832026875,
				7.905935050391939
			],
			"rotation": {
				"angle": 0,
				"axis": "y",
				"origin": [
					8.026875699888018,
					-3.4759238521836515,
					-0.30459126539753534
				]
			},
			"faces": {
				"north": {
					"uv": [
						4.25,
						13.625,
						4.3125,
						13.6875
					],
					"texture": "#0"
				},
				"east": {
					"uv": [
						2.125,
						13.5,
						2.25,
						13.5625
					],
					"texture": "#0"
				},
				"south": {
					"uv": [
						13.625,
						4.25,
						13.6875,
						4.3125
					],
					"texture": "#0"
				},
				"west": {
					"uv": [
						2.25,
						13.5,
						2.375,
						13.5625
					],
					"texture": "#0"
				},
				"up": {
					"uv": [
						2.4375,
						13.625,
						2.375,
						13.5
					],
					"texture": "#0"
				},
				"down": {
					"uv": [
						2.5625,
						13.5,
						2.5,
						13.625
					],
					"texture": "#0"
				}
			}
		},
		{
			"from": [
				8.184770436730123,
				1.1030235162374016,
				7.274356103023518
			],
			"to": [
				8.500559910414333,
				1.4188129899216122,
				7.905935050391939
			],
			"rotation": {
				"angle": 0,
				"axis": "y",
				"origin": [
					8.026875699888018,
					-3.4759238521836515,
					-0.30459126539753534
				]
			},
			"faces": {
				"north": {
					"uv": [
						4.125,
						13.625,
						4.1875,
						13.6875
					],
					"texture": "#0"
				},
				"east": {
					"uv": [
						1.5,
						13.5,
						1.625,
						13.5625
					],
					"texture": "#0"
				},
				"south": {
					"uv": [
						13.625,
						4.125,
						13.6875,
						4.1875
					],
					"texture": "#0"
				},
				"west": {
					"uv": [
						1.625,
						13.5,
						1.75,
						13.5625
					],
					"texture": "#0"
				},
				"up": {
					"uv": [
						1.8125,
						13.625,
						1.75,
						13.5
					],
					"texture": "#0"
				},
				"down": {
					"uv": [
						2.0625,
						13.5,
						2,
						13.625
					],
					"texture": "#0"
				}
			}
		},
		{
			"from": [
				6.29003359462486,
				1.1030235162374016,
				7.274356103023518
			],
			"to": [
				6.60582306830907,
				1.4188129899216122,
				7.905935050391939
			],
			"rotation": {
				"angle": 0,
				"axis": "y",
				"origin": [
					8.026875699888018,
					-3.4759238521836515,
					-0.30459126539753534
				]
			},
			"faces": {
				"north": {
					"uv": [
						4,
						13.625,
						4.0625,
						13.6875
					],
					"texture": "#0"
				},
				"east": {
					"uv": [
						1,
						13.5,
						1.125,
						13.5625
					],
					"texture": "#0"
				},
				"south": {
					"uv": [
						13.625,
						4,
						13.6875,
						4.0625
					],
					"texture": "#0"
				},
				"west": {
					"uv": [
						1.125,
						13.5,
						1.25,
						13.5625
					],
					"texture": "#0"
				},
				"up": {
					"uv": [
						1.3125,
						13.625,
						1.25,
						13.5
					],
					"texture": "#0"
				},
				"down": {
					"uv": [
						1.4375,
						13.5,
						1.375,
						13.625
					],
					"texture": "#0"
				}
			}
		},
		{
			"from": [
				10.553191489361701,
				-3.4759238521836515,
				6.6427771556550965
			],
			"to": [
				13.079507278835386,
				4.103023516237402,
				10.432250839865622
			],
			"rotation": {
				"angle": 0,
				"axis": "y",
				"origin": [
					8.026875699888018,
					-3.4759238521836515,
					-0.30459126539753534
				]
			},
			"faces": {
				"north": {
					"uv": [
						10.25,
						1.5,
						10.75,
						3
					],
					"texture": "#0"
				},
				"east": {
					"uv": [
						8.5,
						0,
						9.25,
						1.5
					],
					"texture": "#0"
				},
				"south": {
					"uv": [
						10.25,
						3,
						10.75,
						4.5
					],
					"texture": "#0"
				},
				"west": {
					"uv": [
						1.75,
						8.5,
						2.5,
						10
					],
					"texture": "#0"
				},
				"up": {
					"uv": [
						1,
						13.25,
						0.5,
						12.5
					],
					"texture": "#0"
				},
				"down": {
					"uv": [
						2,
						12.5,
						1.5,
						13.25
					],
					"texture": "#0"
				}
			}
		},
		{
			"from": [
				10.553191489361701,
				4.103023516237402,
				7.905935050391939
			],
			"to": [
				13.079507278835386,
				11.681970884658455,
				10.432250839865622
			],
			"rotation": {
				"angle": 0,
				"axis": "y",
				"origin": [
					8.026875699888018,
					-3.4759238521836515,
					-0.30459126539753534
				]
			},
			"faces": {
				"north": {
					"uv": [
						10.375,
						9.25,
						10.875,
						10.75
					],
					"texture": "#0"
				},
				"east": {
					"uv": [
						10.75,
						1.5,
						11.25,
						3
					],
					"texture": "#0"
				},
				"south": {
					"uv": [
						2.25,
						10.75,
						2.75,
						12.25
					],
					"texture": "#0"
				},
				"west": {
					"uv": [
						2.75,
						10.75,
						3.25,
						12.25
					],
					"texture": "#0"
				},
				"up": {
					"uv": [
						4.5,
						13.5,
						4,
						13
					],
					"texture": "#0"
				},
				"down": {
					"uv": [
						5,
						13,
						4.5,
						13.5
					],
					"texture": "#0"
				}
			}
		},
		{
			"from": [
				2.97424412094065,
				-3.4759238521836515,
				6.6427771556550965
			],
			"to": [
				5.500559910414333,
				4.103023516237402,
				10.432250839865622
			],
			"rotation": {
				"angle": 0,
				"axis": "y",
				"origin": [
					8.026875699888018,
					-3.4759238521836515,
					-0.30459126539753534
				]
			},
			"faces": {
				"north": {
					"uv": [
						10.75,
						3,
						11.25,
						4.5
					],
					"texture": "#0"
				},
				"east": {
					"uv": [
						2.5,
						8.5,
						3.25,
						10
					],
					"texture": "#0"
				},
				"south": {
					"uv": [
						4,
						10.75,
						4.5,
						12.25
					],
					"texture": "#0"
				},
				"west": {
					"uv": [
						8.5,
						3.5,
						9.25,
						5
					],
					"texture": "#0"
				},
				"up": {
					"uv": [
						6.875,
						13.25,
						6.375,
						12.5
					],
					"texture": "#0"
				},
				"down": {
					"uv": [
						8.125,
						12.5,
						7.625,
						13.25
					],
					"texture": "#0"
				}
			}
		},
		{
			"from": [
				2.97424412094065,
				4.103023516237402,
				7.905935050391939
			],
			"to": [
				5.500559910414333,
				11.681970884658455,
				10.432250839865622
			],
			"rotation": {
				"angle": 0,
				"axis": "y",
				"origin": [
					8.026875699888018,
					-3.4759238521836515,
					-0.30459126539753534
				]
			},
			"faces": {
				"north": {
					"uv": [
						4.5,
						10.75,
						5,
						12.25
					],
					"texture": "#0"
				},
				"east": {
					"uv": [
						10.75,
						7.25,
						11.25,
						8.75
					],
					"texture": "#0"
				},
				"south": {
					"uv": [
						10.375,
						10.75,
						10.875,
						12.25
					],
					"texture": "#0"
				},
				"west": {
					"uv": [
						10.875,
						8.75,
						11.375,
						10.25
					],
					"texture": "#0"
				},
				"up": {
					"uv": [
						13.5,
						7.75,
						13,
						7.25
					],
					"texture": "#0"
				},
				"down": {
					"uv": [
						13.5,
						7.75,
						13,
						8.25
					],
					"texture": "#0"
				}
			}
		},
		{
			"from": [
				5.500559910414333,
				11.681970884658455,
				9.169092945128781
			],
			"to": [
				10.553191489361701,
				16.73460246360582,
				10.432250839865622
			],
			"rotation": {
				"angle": 0,
				"axis": "y",
				"origin": [
					8.026875699888018,
					-3.4759238521836515,
					-0.30459126539753534
				]
			},
			"faces": {
				"north": {
					"uv": [
						9.25,
						0,
						10.25,
						1
					],
					"texture": "#0"
				},
				"east": {
					"uv": [
						4,
						8,
						4.25,
						9
					],
					"texture": "#0"
				},
				"south": {
					"uv": [
						9.25,
						3.5,
						10.25,
						4.5
					],
					"texture": "#0"
				},
				"west": {
					"uv": [
						7.375,
						12.75,
						7.625,
						13.75
					],
					"texture": "#0"
				},
				"up": {
					"uv": [
						13.75,
						5.75,
						12.75,
						5.5
					],
					"texture": "#0"
				},
				"down": {
					"uv": [
						13.875,
						4.75,
						12.875,
						5
					],
					"texture": "#0"
				}
			}
		},
		{
			"from": [
				10.553191489361701,
				11.681970884658455,
				6.6427771556550965
			],
			"to": [
				13.079507278835386,
				16.73460246360582,
				10.432250839865622
			],
			"rotation": {
				"angle": 0,
				"axis": "y",
				"origin": [
					8.026875699888018,
					-3.4759238521836515,
					-0.30459126539753534
				]
			},
			"faces": {
				"north": {
					"uv": [
						8.75,
						11.25,
						9.25,
						12.25
					],
					"texture": "#0"
				},
				"east": {
					"uv": [
						10.875,
						10.25,
						11.625,
						11.25
					],
					"texture": "#0"
				},
				"south": {
					"uv": [
						11.375,
						8.75,
						11.875,
						9.75
					],
					"texture": "#0"
				},
				"west": {
					"uv": [
						11,
						0,
						11.75,
						1
					],
					"texture": "#0"
				},
				"up": {
					"uv": [
						8.625,
						13.25,
						8.125,
						12.5
					],
					"texture": "#0"
				},
				"down": {
					"uv": [
						11.375,
						12.5,
						10.875,
						13.25
					],
					"texture": "#0"
				}
			}
		},
		{
			"from": [
				2.97424412094065,
				11.681970884658455,
				6.6427771556550965
			],
			"to": [
				5.500559910414333,
				16.73460246360582,
				10.432250839865622
			],
			"rotation": {
				"angle": 0,
				"axis": "y",
				"origin": [
					8.026875699888018,
					-3.4759238521836515,
					-0.30459126539753534
				]
			},
			"faces": {
				"north": {
					"uv": [
						0,
						11.5,
						0.5,
						12.5
					],
					"texture": "#0"
				},
				"east": {
					"uv": [
						1.5,
						11,
						2.25,
						12
					],
					"texture": "#0"
				},
				"south": {
					"uv": [
						0.5,
						11.5,
						1,
						12.5
					],
					"texture": "#0"
				},
				"west": {
					"uv": [
						11,
						5,
						11.75,
						6
					],
					"texture": "#0"
				},
				"up": {
					"uv": [
						11.875,
						13.25,
						11.375,
						12.5
					],
					"texture": "#0"
				},
				"down": {
					"uv": [
						12.375,
						12.5,
						11.875,
						13.25
					],
					"texture": "#0"
				}
			}
		},
		{
			"from": [
				13.079507278835386,
				-3.4759238521836515,
				6.6427771556550965
			],
			"to": [
				14.342665173572229,
				16.73460246360582,
				10.432250839865622
			],
			"rotation": {
				"angle": 0,
				"axis": "y",
				"origin": [
					8.026875699888018,
					-3.4759238521836515,
					-0.30459126539753534
				]
			},
			"faces": {
				"north": {
					"uv": [
						5.25,
						9.5,
						5.5,
						13.5
					],
					"texture": "#0"
				},
				"east": {
					"uv": [
						5.25,
						0,
						6,
						4
					],
					"texture": "#0"
				},
				"south": {
					"uv": [
						5.5,
						9.5,
						5.75,
						13.5
					],
					"texture": "#0"
				},
				"west": {
					"uv": [
						5.25,
						4,
						6,
						8
					],
					"texture": "#0"
				},
				"up": {
					"uv": [
						10.125,
						13.75,
						9.875,
						13
					],
					"texture": "#0"
				},
				"down": {
					"uv": [
						10.625,
						13,
						10.375,
						13.75
					],
					"texture": "#0"
				}
			}
		},
		{
			"from": [
				1.7110862262038076,
				-3.4759238521836515,
				6.6427771556550965
			],
			"to": [
				2.97424412094065,
				16.73460246360582,
				10.432250839865622
			],
			"rotation": {
				"angle": 0,
				"axis": "y",
				"origin": [
					8.026875699888018,
					-3.4759238521836515,
					-0.30459126539753534
				]
			},
			"faces": {
				"north": {
					"uv": [
						5.75,
						9.5,
						6,
						13.5
					],
					"texture": "#0"
				},
				"east": {
					"uv": [
						0,
						6,
						0.75,
						10
					],
					"texture": "#0"
				},
				"south": {
					"uv": [
						6,
						9.5,
						6.25,
						13.5
					],
					"texture": "#0"
				},
				"west": {
					"uv": [
						6,
						0,
						6.75,
						4
					],
					"texture": "#0"
				},
				"up": {
					"uv": [
						10.875,
						13.75,
						10.625,
						13
					],
					"texture": "#0"
				},
				"down": {
					"uv": [
						12.625,
						13,
						12.375,
						13.75
					],
					"texture": "#0"
				}
			}
		},
		{
			"from": [
				1.7110862262038076,
				16.73460246360582,
				6.6427771556550965
			],
			"to": [
				14.342665173572229,
				17.997760358342664,
				10.432250839865622
			],
			"rotation": {
				"angle": 0,
				"axis": "y",
				"origin": [
					8.026875699888018,
					-3.4759238521836515,
					-0.30459126539753534
				]
			},
			"faces": {
				"north": {
					"uv": [
						11.25,
						1.5,
						13.75,
						1.75
					],
					"texture": "#0"
				},
				"east": {
					"uv": [
						13.25,
						0.25,
						14,
						0.5
					],
					"texture": "#0"
				},
				"south": {
					"uv": [
						11.25,
						1.75,
						13.75,
						2
					],
					"texture": "#0"
				},
				"west": {
					"uv": [
						13.25,
						2,
						14,
						2.25
					],
					"texture": "#0"
				},
				"up": {
					"uv": [
						8.5,
						6.25,
						6,
						5.5
					],
					"texture": "#0"
				},
				"down": {
					"uv": [
						8.5,
						6.25,
						6,
						7
					],
					"texture": "#0"
				}
			}
		},
		{
			"from": [
				2.97424412094065,
				17.997760358342664,
				6.6427771556550965
			],
			"to": [
				13.079507278835386,
				19.260918253079506,
				10.432250839865622
			],
			"rotation": {
				"angle": 0,
				"axis": "y",
				"origin": [
					8.026875699888018,
					-3.4759238521836515,
					-0.30459126539753534
				]
			},
			"faces": {
				"north": {
					"uv": [
						11.375,
						9.75,
						13.375,
						10
					],
					"texture": "#0"
				},
				"east": {
					"uv": [
						13.25,
						2.25,
						14,
						2.5
					],
					"texture": "#0"
				},
				"south": {
					"uv": [
						11.375,
						10,
						13.375,
						10.25
					],
					"texture": "#0"
				},
				"west": {
					"uv": [
						13.25,
						2.75,
						14,
						3
					],
					"texture": "#0"
				},
				"up": {
					"uv": [
						8,
						7.75,
						6,
						7
					],
					"texture": "#0"
				},
				"down": {
					"uv": [
						8,
						7.75,
						6,
						8.5
					],
					"texture": "#0"
				}
			}
		},
		{
			"from": [
				4.2374020156774925,
				19.260918253079506,
				6.6427771556550965
			],
			"to": [
				11.816349384098544,
				20.52407614781635,
				10.432250839865622
			],
			"rotation": {
				"angle": 0,
				"axis": "y",
				"origin": [
					8.026875699888018,
					-3.4759238521836515,
					-0.30459126539753534
				]
			},
			"faces": {
				"north": {
					"uv": [
						12.375,
						1.25,
						13.875,
						1.5
					],
					"texture": "#0"
				},
				"east": {
					"uv": [
						13.25,
						3,
						14,
						3.25
					],
					"texture": "#0"
				},
				"south": {
					"uv": [
						12.375,
						6.5,
						13.875,
						6.75
					],
					"texture": "#0"
				},
				"west": {
					"uv": [
						13.25,
						3.25,
						14,
						3.5
					],
					"texture": "#0"
				},
				"up": {
					"uv": [
						10,
						5.75,
						8.5,
						5
					],
					"texture": "#0"
				},
				"down": {
					"uv": [
						10,
						5.75,
						8.5,
						6.5
					],
					"texture": "#0"
				}
			}
		}
	],
	"display": {
		"head": {
			"rotation": [
				0,
				180,
				0
			]
		}
	}
}