{"textures":{"0":"modelengine:entity/star_guardian"},"elements":[{"from":[4.8908587,5.378607,4.5],"to":[12.390859,7.628607,11.5],"faces":{"east":{"uv":[12.375,12.125,13.25,12.375],"tintindex":0,"rotation":0,"texture":"#0"},"south":{"uv":[12.25,11.625,13.25,11.875],"tintindex":0,"rotation":0,"texture":"#0"},"north":{"uv":[12.25,11.375,13.25,11.625],"tintindex":0,"rotation":0,"texture":"#0"},"west":{"uv":[12.375,12.375,13.25,12.625],"tintindex":0,"rotation":0,"texture":"#0"},"up":{"uv":[7.75,9.375,6.75,8.5],"tintindex":0,"rotation":0,"texture":"#0"},"down":{"uv":[9.5,7.25,8.5,8.125],"tintindex":0,"rotation":0,"texture":"#0"}}},{"from":[6.3908587,-4.871393,5.5],"to":[11.390859,7.128607,10.5],"faces":{"east":{"uv":[8.125,2.75,8.75,4.25],"tintindex":0,"rotation":0,"texture":"#0"},"south":{"uv":[3.0,8.125,3.625,9.625],"tintindex":0,"rotation":0,"texture":"#0"},"north":{"uv":[8.125,1.25,8.75,2.75],"tintindex":0,"rotation":0,"texture":"#0"},"west":{"uv":[4.75,8.125,5.375,9.625],"tintindex":0,"rotation":0,"texture":"#0"},"up":{"uv":[12.25,12.125,11.625,11.5],"tintindex":0,"rotation":0,"texture":"#0"},"down":{"uv":[1.875,11.75,1.25,12.375],"tintindex":0,"rotation":0,"texture":"#0"}}},{"from":[4.6408587,-4.871393,6.0],"to":[8.390859,7.128607,10.0],"faces":{"east":{"uv":[0.0,9.75,0.5,11.25],"tintindex":0,"rotation":0,"texture":"#0"},"south":{"uv":[0.5,9.75,1.0,11.25],"tintindex":0,"rotation":0,"texture":"#0"},"north":{"uv":[6.0,9.625,6.5,11.125],"tintindex":0,"rotation":0,"texture":"#0"},"west":{"uv":[9.75,0.75,10.25,2.25],"tintindex":0,"rotation":0,"texture":"#0"},"up":{"uv":[12.875,0.5,12.375,0.0],"tintindex":0,"rotation":0,"texture":"#0"},"down":{"uv":[12.875,0.5,12.375,1.0],"tintindex":0,"rotation":0,"texture":"#0"}},"rotation":{"origin":[5.8908587,1.1286068,8.0],"angle":22.5,"axis":"z"}}],"display":{"gui":{"rotation":[30,225,0]}}}