{"textures":{"0":"modelengine:entity/90s"},"elements":[{"from":[8.7877,7.375,7.8723],"to":[10.2877,9.125,8.3723],"faces":{"east":{"uv":[4.0,12.75,4.125,13.1875],"tintindex":0,"rotation":0,"texture":"#0"},"south":{"uv":[10.25,6.75,10.625,7.1875],"tintindex":0,"rotation":0,"texture":"#0"},"north":{"uv":[5.75,10.25,6.125,10.6875],"tintindex":0,"rotation":0,"texture":"#0"},"west":{"uv":[5.25,12.75,5.375,13.1875],"tintindex":0,"rotation":0,"texture":"#0"},"up":{"uv":[13.375,1.125,13.0,1.0],"tintindex":0,"rotation":0,"texture":"#0"},"down":{"uv":[2.875,13.0,2.5,13.125],"tintindex":0,"rotation":0,"texture":"#0"}}},{"from":[11.6126995,7.875,7.5973],"to":[12.6126995,10.875,8.0973],"faces":{"east":{"uv":[1.25,11.75,1.375,12.5],"tintindex":0,"rotation":0,"texture":"#0"},"south":{"uv":[6.25,10.0,6.5,10.75],"tintindex":0,"rotation":0,"texture":"#0"},"north":{"uv":[10.0,5.5,10.25,6.25],"tintindex":0,"rotation":0,"texture":"#0"},"west":{"uv":[1.5,11.75,1.625,12.5],"tintindex":0,"rotation":0,"texture":"#0"},"up":{"uv":[13.75,1.375,13.5,1.25],"tintindex":0,"rotation":0,"texture":"#0"},"down":{"uv":[2.0,13.5,1.75,13.625],"tintindex":0,"rotation":0,"texture":"#0"}},"rotation":{"origin":[11.0377,9.125,8.1223],"angle":-22.5,"axis":"y"}},{"from":[7.2876997,7.625,7.8723],"to":[8.7877,8.625,8.3723],"faces":{"east":{"uv":[2.0,13.5,2.125,13.75],"tintindex":0,"rotation":0,"texture":"#0"},"south":{"uv":[11.75,1.25,12.125,1.5],"tintindex":0,"rotation":0,"texture":"#0"},"north":{"uv":[11.5,11.25,11.875,11.5],"tintindex":0,"rotation":0,"texture":"#0"},"west":{"uv":[2.5,13.5,2.625,13.75],"tintindex":0,"rotation":0,"texture":"#0"},"up":{"uv":[3.375,13.125,3.0,13.0],"tintindex":0,"rotation":0,"texture":"#0"},"down":{"uv":[5.125,13.0,4.75,13.125],"tintindex":0,"rotation":0,"texture":"#0"}}},{"from":[13.03242,9.125,10.09834],"to":[14.032419,11.625,10.59834],"faces":{"east":{"uv":[12.0,6.0,12.125,6.625],"tintindex":0,"rotation":0,"texture":"#0"},"south":{"uv":[8.0,10.25,8.25,10.875],"tintindex":0,"rotation":0,"texture":"#0"},"north":{"uv":[7.75,10.25,8.0,10.875],"tintindex":0,"rotation":0,"texture":"#0"},"west":{"uv":[7.25,12.0,7.375,12.625],"tintindex":0,"rotation":0,"texture":"#0"},"up":{"uv":[0.5,13.625,0.25,13.5],"tintindex":0,"rotation":0,"texture":"#0"},"down":{"uv":[13.75,0.25,13.5,0.375],"tintindex":0,"rotation":0,"texture":"#0"}},"rotation":{"origin":[13.53242,10.125,10.34834],"angle":-45.0,"axis":"y"}},{"from":[10.2877,7.625,7.8723],"to":[11.7877,10.625,8.3723],"faces":{"east":{"uv":[1.75,11.75,1.875,12.5],"tintindex":0,"rotation":0,"texture":"#0"},"south":{"uv":[9.0,6.0,9.375,6.75],"tintindex":0,"rotation":0,"texture":"#0"},"north":{"uv":[9.0,5.25,9.375,6.0],"tintindex":0,"rotation":0,"texture":"#0"},"west":{"uv":[2.0,11.75,2.125,12.5],"tintindex":0,"rotation":0,"texture":"#0"},"up":{"uv":[13.375,0.625,13.0,0.5],"tintindex":0,"rotation":0,"texture":"#0"},"down":{"uv":[13.375,0.75,13.0,0.875],"tintindex":0,"rotation":0,"texture":"#0"}}},{"from":[13.235893,8.375,8.331915],"to":[14.235892,11.375,8.831915],"faces":{"east":{"uv":[0.5,11.75,0.625,12.5],"tintindex":0,"rotation":0,"texture":"#0"},"south":{"uv":[4.25,10.0,4.5,10.75],"tintindex":0,"rotation":0,"texture":"#0"},"north":{"uv":[10.0,4.0,10.25,4.75],"tintindex":0,"rotation":0,"texture":"#0"},"west":{"uv":[11.75,0.5,11.875,1.25],"tintindex":0,"rotation":0,"texture":"#0"},"up":{"uv":[0.75,13.625,0.5,13.5],"tintindex":0,"rotation":0,"texture":"#0"},"down":{"uv":[13.75,0.5,13.5,0.625],"tintindex":0,"rotation":0,"texture":"#0"}},"rotation":{"origin":[12.860893,9.625,8.756915],"angle":-45.0,"axis":"y"}},{"from":[12.486109,8.125,7.854618],"to":[13.486109,11.125,8.354618],"faces":{"east":{"uv":[0.75,11.75,0.875,12.5],"tintindex":0,"rotation":0,"texture":"#0"},"south":{"uv":[10.0,4.75,10.25,5.5],"tintindex":0,"rotation":0,"texture":"#0"},"north":{"uv":[4.5,10.0,4.75,10.75],"tintindex":0,"rotation":0,"texture":"#0"},"west":{"uv":[1.0,11.75,1.125,12.5],"tintindex":0,"rotation":0,"texture":"#0"},"up":{"uv":[13.75,0.875,13.5,0.75],"tintindex":0,"rotation":0,"texture":"#0"},"down":{"uv":[13.75,1.0,13.5,1.125],"tintindex":0,"rotation":0,"texture":"#0"}},"rotation":{"origin":[12.136108,9.375,8.279618],"angle":-45.0,"axis":"y"}}],"display":{"gui":{"rotation":[30,225,0]}}}