{"variants":{"west=true,up=true,south=true,north=true,east=true,down=true":{"model":"block/original/chorus_plant"},"down=false,east=false,north=false,south=false,up=false,west=true":{"model":"myitems:ia_auto_gen/aureate_leaves"},"down=false,east=false,north=false,south=true,up=true,west=true":{"model":"myitems:ia_auto_gen/berly_wood_leaves"},"down=false,east=false,north=false,south=false,up=true,west=true":{"model":"myitems:ia_auto_gen/dusk_wood_leaves"},"down=false,east=false,north=false,south=true,up=false,west=false":{"model":"myitems:ia_auto_gen/pride_wood_leaves"},"down=false,east=false,north=false,south=true,up=false,west=true":{"model":"myitems:ia_auto_gen/saxe_wood_leaves"},"down=false,east=false,north=false,south=true,up=true,west=false":{"model":"myitems:ia_auto_gen/shadespire_wood_leaves"}}}